uwsgidecorators.py
pyuwsgi.cpython-39-darwin.so
pyuwsgi-2.0.30.dist-info/RECORD
pyuwsgi-2.0.30.dist-info/WHEEL
pyuwsgi-2.0.30.dist-info/entry_points.txt
pyuwsgi-2.0.30.dist-info/top_level.txt
pyuwsgi-2.0.30.dist-info/METADATA
pyuwsgi-2.0.30.dist-info/licenses/LICENSE
pyuwsgi.dylibs/libpcre2-8.0.dylib
pyuwsgi.dylibs/libjansson.4.dylib
